annotation_editor/__init__.py
annotation_editor/example.py
annotation_editor/helper.py
annotation_editor/frontend/build/asset-manifest.json
annotation_editor/frontend/build/bootstrap.min.css
annotation_editor/frontend/build/index.html
annotation_editor/frontend/build/static/css/main.0dc8a624.css
annotation_editor/frontend/build/static/css/main.0dc8a624.css.map
annotation_editor/frontend/build/static/js/main.abf7fb03.js
annotation_editor/frontend/build/static/js/main.abf7fb03.js.LICENSE.txt
annotation_editor/frontend/build/static/js/main.abf7fb03.js.map
annotation_editor/frontend/build/static/media/arrow.558353d8d70a4aebd703.svg
annotation_editor/frontend/build/static/media/cross.795387577400f42d9ba634dd622972fd.svg
annotation_editor/frontend/build/static/media/user.3da91e8a624c8c053df876cafd905998.svg
streamlit_annotation_editor-0.1.4.dist-info/LICENSE
streamlit_annotation_editor-0.1.4.dist-info/METADATA
streamlit_annotation_editor-0.1.4.dist-info/WHEEL
streamlit_annotation_editor-0.1.4.dist-info/top_level.txt
streamlit_annotation_editor-0.1.4.dist-info/RECORD
